LLDT/__init__.py
LLDT/df_to_list_of_dictionary/__init__.py
LLDT/df_to_list_of_dictionary/df_to_list_of_dict.cp38-win_amd64.pyd
LLDT/df_to_string/__init__.py
LLDT/df_to_string/df_to_string.cp38-win_amd64.pyd
LLDT/string_to_df/__init__.py
LLDT/string_to_df/string_to_df.cp38-win_amd64.pyd
LLDT-0.0.7.dist-info/LICENSE.txt
LLDT-0.0.7.dist-info/METADATA
LLDT-0.0.7.dist-info/WHEEL
LLDT-0.0.7.dist-info/top_level.txt
LLDT-0.0.7.dist-info/RECORD
