Metadata-Version: 2.1
Name: LLDT
Version: 0.0.7
Summary: The package will change the world of data transformation by utilizing/modifying the low-level stuff.
Home-page: https://github.com/mdAshif1998/lowLevelDataTransformation/tree/master
Author: Md Ashif Ali
Author-email: mdashifali.dml25@iiitb.net
License: UNKNOWN
Keywords: python,data,transformation,cython
Platform: UNKNOWN
Classifier: Intended Audience :: Developers
Classifier: Programming Language :: Python :: 3
Classifier: Programming Language :: Python :: 3.7
Classifier: Programming Language :: Python :: 3.8
Classifier: Programming Language :: Python :: 3.9
Classifier: Programming Language :: Python :: 3.10
Classifier: Programming Language :: Python :: 3.11
Classifier: Programming Language :: Python :: 3.12
Classifier: License :: OSI Approved :: MIT License
Classifier: Operating System :: OS Independent
Classifier: Topic :: Utilities
Requires-Python: >=3.7
Requires-Dist: Cython
Requires-Dist: numpy
Requires-Dist: pandas
